{
	"absolute": {
		"style": {
			"position": "absolute"
		}
	},
	"relative": {
		"style": {
			"position": "relative"
		}
	},
	"bottom-5": {
		"style": {
			"bottom": 20
		}
	},
	"right-5": {
		"style": {
			"right": 20
		}
	},
	"left-[40%]": {
		"style": {
			"left": "40%"
		}
	},
	"top-[40%]": {
		"style": {
			"top": "40%"
		}
	},
	"m-2": {
		"style": {
			"marginTop": 8,
			"marginRight": 8,
			"marginBottom": 8,
			"marginLeft": 8
		}
	},
	"my-2": {
		"style": {
			"marginTop": 8,
			"marginBottom": 8
		}
	},
	"mx-0": {
		"style": {
			"marginLeft": 0,
			"marginRight": 0
		}
	},
	"mx-[2px]": {
		"style": {
			"marginLeft": 2,
			"marginRight": 2
		}
	},
	"my-4": {
		"style": {
			"marginTop": 16,
			"marginBottom": 16
		}
	},
	"mx-1": {
		"style": {
			"marginLeft": 4,
			"marginRight": 4
		}
	},
	"my-3": {
		"style": {
			"marginTop": 12,
			"marginBottom": 12
		}
	},
	"mx-2": {
		"style": {
			"marginLeft": 8,
			"marginRight": 8
		}
	},
	"my-1": {
		"style": {
			"marginTop": 4,
			"marginBottom": 4
		}
	},
	"mb-12": {
		"style": {
			"marginBottom": 48
		}
	},
	"mt-4": {
		"style": {
			"marginTop": 16
		}
	},
	"ml-2": {
		"style": {
			"marginLeft": 8
		}
	},
	"mt-2": {
		"style": {
			"marginTop": 8
		}
	},
	"mt-3": {
		"style": {
			"marginTop": 12
		}
	},
	"mt-1": {
		"style": {
			"marginTop": 4
		}
	},
	"mt-5": {
		"style": {
			"marginTop": 20
		}
	},
	"h-[65]": {
		"style": {
			"height": 65
		}
	},
	"h-28": {
		"style": {
			"height": 112
		}
	},
	"h-40": {
		"style": {
			"height": 160
		}
	},
	"h-72": {
		"style": {
			"height": 288
		}
	},
	"h-full": {
		"style": {
			"height": "100%"
		}
	},
	"h-16": {
		"style": {
			"height": 64
		}
	},
	"h-64": {
		"style": {
			"height": 256
		}
	},
	"w-24": {
		"style": {
			"width": 96
		}
	},
	"w-40": {
		"style": {
			"width": 160
		}
	},
	"w-full": {
		"style": {
			"width": "100%"
		}
	},
	"w-16": {
		"style": {
			"width": 64
		}
	},
	"flex-1": {
		"style": {
			"flexGrow": 1,
			"flexShrink": 1,
			"flexBasis": "0%"
		}
	},
	"flex-row": {
		"style": {
			"flexDirection": "row"
		}
	},
	"flex-col": {
		"style": {
			"flexDirection": "column"
		}
	},
	"flex-wrap": {
		"style": {
			"flexWrap": "wrap"
		}
	},
	"items-center": {
		"style": {
			"alignItems": "center"
		}
	},
	"justify-end": {
		"style": {
			"justifyContent": "flex-end"
		}
	},
	"justify-center": {
		"style": {
			"justifyContent": "center"
		}
	},
	"justify-between": {
		"style": {
			"justifyContent": "space-between"
		}
	},
	"self-center": {
		"style": {
			"alignSelf": "center"
		}
	},
	"rounded-lg": {
		"style": {
			"borderTopLeftRadius": 8,
			"borderTopRightRadius": 8,
			"borderBottomRightRadius": 8,
			"borderBottomLeftRadius": 8
		}
	},
	"rounded-full": {
		"style": {
			"borderTopLeftRadius": 9999,
			"borderTopRightRadius": 9999,
			"borderBottomRightRadius": 9999,
			"borderBottomLeftRadius": 9999
		}
	},
	"rounded-t-3xl": {
		"style": {
			"borderTopLeftRadius": 24,
			"borderTopRightRadius": 24
		}
	},
	"border-b-[.5px]": {
		"style": {
			"borderBottomWidth": 0.5
		}
	},
	"border-white": {
		"style": {
			"--tw-border-opacity": 1,
			"borderTopColor": "rgb(255 255 255 / var(--tw-border-opacity))",
			"borderRightColor": "rgb(255 255 255 / var(--tw-border-opacity))",
			"borderBottomColor": "rgb(255 255 255 / var(--tw-border-opacity))",
			"borderLeftColor": "rgb(255 255 255 / var(--tw-border-opacity))"
		}
	},
	"bg-red": {
		"style": {
			"--tw-bg-opacity": 1,
			"backgroundColor": "rgb(226 25 56 / var(--tw-bg-opacity))"
		}
	},
	"bg-black": {
		"style": {
			"--tw-bg-opacity": 1,
			"backgroundColor": "rgb(0 0 0 / var(--tw-bg-opacity))"
		}
	},
	"bg-grayDark": {
		"style": {
			"--tw-bg-opacity": 1,
			"backgroundColor": "rgb(27 26 31 / var(--tw-bg-opacity))"
		}
	},
	"bg-white": {
		"style": {
			"--tw-bg-opacity": 1,
			"backgroundColor": "rgb(255 255 255 / var(--tw-bg-opacity))"
		}
	},
	"bg-dark": {
		"style": {
			"--tw-bg-opacity": 1,
			"backgroundColor": "rgb(12 12 12 / var(--tw-bg-opacity))"
		}
	},
	"bg-opacity-10": {
		"style": {
			"--tw-bg-opacity": 0.1
		}
	},
	"bg-opacity-50": {
		"style": {
			"--tw-bg-opacity": 0.5
		}
	},
	"bg-opacity-30": {
		"style": {
			"--tw-bg-opacity": 0.3
		}
	},
	"p-2": {
		"style": {
			"paddingTop": 8,
			"paddingRight": 8,
			"paddingBottom": 8,
			"paddingLeft": 8
		}
	},
	"p-3": {
		"style": {
			"paddingTop": 12,
			"paddingRight": 12,
			"paddingBottom": 12,
			"paddingLeft": 12
		}
	},
	"p-4": {
		"style": {
			"paddingTop": 16,
			"paddingRight": 16,
			"paddingBottom": 16,
			"paddingLeft": 16
		}
	},
	"p-5": {
		"style": {
			"paddingTop": 20,
			"paddingRight": 20,
			"paddingBottom": 20,
			"paddingLeft": 20
		}
	},
	"px-4": {
		"style": {
			"paddingLeft": 16,
			"paddingRight": 16
		}
	},
	"py-2": {
		"style": {
			"paddingTop": 8,
			"paddingBottom": 8
		}
	},
	"px-2": {
		"style": {
			"paddingLeft": 8,
			"paddingRight": 8
		}
	},
	"pt-2": {
		"style": {
			"paddingTop": 8
		}
	},
	"pt-4": {
		"style": {
			"paddingTop": 16
		}
	},
	"text-center": {
		"style": {
			"textAlign": "center"
		}
	},
	"font-nunito-bold": {
		"style": {
			"fontFamily": "nunito-bold"
		}
	},
	"font-nunito-medium": {
		"style": {
			"fontFamily": "nunito-medium"
		}
	},
	"text-lg": {
		"style": {
			"fontSize": 18
		}
	},
	"text-sm": {
		"style": {
			"fontSize": 12
		}
	},
	"text-2xl": {
		"style": {
			"fontSize": 22
		}
	},
	"text-base": {
		"style": {
			"fontSize": 14
		}
	},
	"text-xs": {
		"style": {
			"fontSize": 10
		}
	},
	"text-md": {
		"style": {
			"fontSize": 16
		}
	},
	"text-xl": {
		"style": {
			"fontSize": 20
		}
	},
	"text-gray-300": {
		"style": {
			"--tw-text-opacity": 1,
			"color": "rgb(209 213 219 / var(--tw-text-opacity))"
		}
	},
	"text-gray-400": {
		"style": {
			"--tw-text-opacity": 1,
			"color": "rgb(156 163 175 / var(--tw-text-opacity))"
		}
	},
	"text-red": {
		"style": {
			"--tw-text-opacity": 1,
			"color": "rgb(226 25 56 / var(--tw-text-opacity))"
		}
	},
	"text-white": {
		"style": {
			"--tw-text-opacity": 1,
			"color": "rgb(255 255 255 / var(--tw-text-opacity))"
		}
	},
	"text-gray-500": {
		"style": {
			"--tw-text-opacity": 1,
			"color": "rgb(107 114 128 / var(--tw-text-opacity))"
		}
	}
}